git_fastcdc.py
git_fastcdc-0.5.0.dist-info/LICENSE
git_fastcdc-0.5.0.dist-info/METADATA
git_fastcdc-0.5.0.dist-info/WHEEL
git_fastcdc-0.5.0.dist-info/entry_points.txt
git_fastcdc-0.5.0.dist-info/RECORD
