Metadata-Version: 2.1
Name: git-fastcdc
Version: 0.5.0
Summary: FastCDC for large git files
License: AGPL-3.0-or-later
Author: Jean-Louis Fuchs
Author-email: jean-louis.fuchs@adfinis.com
Requires-Python: >=3.9,<4.0
Classifier: License :: OSI Approved :: GNU Affero General Public License v3 or later (AGPLv3+)
Classifier: Programming Language :: Python :: 3
Classifier: Programming Language :: Python :: 3.9
Classifier: Programming Language :: Python :: 3.10
Classifier: Programming Language :: Python :: 3.11
Classifier: Programming Language :: Python :: 3.12
Requires-Dist: click (>=8.1.7,<9.0.0)
Requires-Dist: fastcdc (>=1.5.0,<2.0.0)
Requires-Dist: tqdm (>=4.66.2,<5.0.0)
